{
  "project_info": {
    "project_number": "775504695277",
    "project_id": "task-management-app-89e1f",
    "storage_bucket": "task-management-app-89e1f.firebasestorage.app"
  },
  "client": [
    {
      "client_info": {
        "mobilesdk_app_id": "1:775504695277:android:d5b0c8496d63229e9c21e4",
        "android_client_info": {
          "package_name": "com.example.task_management_app"
        }
      },
      "oauth_client": [],
      "api_key": [
        {
          "current_key": "AIzaSyBkaLej3pjI-SIOa_slx-uImDgkEmCabmI"
        }
      ],
      "services": {
        "appinvite_service": {
          "other_platform_oauth_client": []
        }
      }
    }
  ],
  "configuration_version": "1"
}